nmrpro/NMRFileManager.py
nmrpro/R.py
nmrpro/__init__.py
nmrpro/decorators.py
nmrpro/exceptions.py
nmrpro/icoshift2.py
nmrpro/ipynb.py
nmrpro/readers.py
nmrpro/utils.py
nmrpro/workflow_manager.py
nmrpro/workflows.py
nmrpro/classes/NMRSpectrum.py
nmrpro/classes/__init__.py
nmrpro/classes/test_classes.py
nmrpro/libs/__init__.py
nmrpro/libs/decorator.py
nmrpro/plugins/JSinput.py
nmrpro/plugins/JSinput2.py
nmrpro/plugins/PluginMount.py
nmrpro/plugins/__init__.py
nmrpro/plugins/FFT/__init__.py
nmrpro/plugins/FFT/fft.py
nmrpro/plugins/FFT/test_fft.py
nmrpro/plugins/ZF/__init__.py
nmrpro/plugins/ZF/test_zf.py
nmrpro/plugins/ZF/zf.py
nmrpro/plugins/apodization/__init__.py
nmrpro/plugins/apodization/apod.py
nmrpro/plugins/apodization/test_apod.py
nmrpro/plugins/baseline/__init__.py
nmrpro/plugins/baseline/bl.py
nmrpro/plugins/baseline/bl_airPLS.py
nmrpro/plugins/peakpick/__init__.py
nmrpro/plugins/peakpick/peakpick.py
nmrpro/plugins/phasing/__init__.py
nmrpro/plugins/phasing/ps.py
nmrpro-0.2.8.dist-info/METADATA
nmrpro-0.2.8.dist-info/WHEEL
nmrpro-0.2.8.dist-info/dependency_links.txt
nmrpro-0.2.8.dist-info/top_level.txt
nmrpro-0.2.8.dist-info/RECORD
