Metadata-Version: 2.1
Name: nmrpro
Version: 0.2.8
Summary: Interactive processing of NMR Spectra
Home-page: https://github.com/ahmohamed/nmrpro
Author: Ahmed Mohamed
Author-email: mohamed@kuicr.kyoto-u.ac.jp
License: MIT
Keywords: nmr,spectra,multi-dimensional
Platform: UNKNOWN
Requires-Dist: numpy
Requires-Dist: scipy
Requires-Dist: nmrglue (>=0.5)
